bytedance_ckpt_io_metrics/__init__.py
bytedance_ckpt_io_metrics-0.0.1.dist-info/METADATA
bytedance_ckpt_io_metrics-0.0.1.dist-info/WHEEL
bytedance_ckpt_io_metrics-0.0.1.dist-info/top_level.txt
bytedance_ckpt_io_metrics-0.0.1.dist-info/RECORD
