Metadata-Version: 2.1
Name: bytedance-ckpt-io-metrics
Version: 0.0.1
Summary: A simple package named bytedance_ckpt_io_metrics
Home-page: https://github.com/artifact/bytedance_ckpt_io_metrics.git
Author: artifact
Author-email: artifact@example.com
License: UNKNOWN
Platform: UNKNOWN
Classifier: Programming Language :: Python :: 3
Classifier: License :: OSI Approved :: MIT License
Classifier: Operating System :: OS Independent
